covidcaput/__init__.py
covidcaput/covid_caput.py
covidcaput-1.1.1.dist-info/METADATA
covidcaput-1.1.1.dist-info/WHEEL
covidcaput-1.1.1.dist-info/top_level.txt
covidcaput-1.1.1.dist-info/RECORD
