Metadata-Version: 2.1
Name: covidcaput
Version: 1.1.1
Summary: Covid Caput!
Home-page: UNKNOWN
Author: Grupa Żywiec Data Science team
Author-email: data.science@grupazywiec.pl
License: MIT
Platform: UNKNOWN
Classifier: License :: OSI Approved :: MIT License
Classifier: Programming Language :: Python
Classifier: Programming Language :: Python :: 3
Classifier: Programming Language :: Python :: 3.6
Classifier: Programming Language :: Python :: Implementation :: CPython
Classifier: Programming Language :: Python :: Implementation :: PyPy
Requires-Python: >=3.6.0
